{"nikola": [1, "/categories/nikola/", {"posts": [{"isodate": "2015-09-21T15:01:00-04:00", "url": "/posts/setting-up-nikola-and-github/", "date": "09/21/2015", "title": "Setting up Nikloa for Personal Github Sites"}]}], "nim": [3, "/categories/nim/", {"posts": [{"isodate": "2015-01-24T10:18:00-04:00", "url": "/posts/connecting-nim-to-python/", "date": "01/24/2015", "title": "Connecting Nim to Python"}, {"isodate": "2015-01-14T13:18:00-04:00", "url": "/posts/getting-started-with-nim-2/", "date": "01/14/2015", "title": "Getting Started With Nim - Part 2"}, {"isodate": "2015-01-05T10:18:00-04:00", "url": "/posts/getting-started-with-nim/", "date": "01/05/2015", "title": "Getting Started With Nim"}]}], "python": [2, "/categories/python/", {"posts": [{"isodate": "2015-09-21T15:01:00-04:00", "url": "/posts/setting-up-nikola-and-github/", "date": "09/21/2015", "title": "Setting up Nikloa for Personal Github Sites"}, {"isodate": "2015-01-24T10:18:00-04:00", "url": "/posts/connecting-nim-to-python/", "date": "01/24/2015", "title": "Connecting Nim to Python"}]}], "github": [1, "/categories/github/", {"posts": [{"isodate": "2015-09-21T15:01:00-04:00", "url": "/posts/setting-up-nikola-and-github/", "date": "09/21/2015", "title": "Setting up Nikloa for Personal Github Sites"}]}]}